setup.py
requirements/__init__.py
requirements/base.txt
requirements/test.txt
tests/integration/__init__.py
tests/integration/test_registry.py
tests/integration/test_service.py
trellio/__init__.py
trellio/bus.py
trellio/exceptions.py
trellio/host.py
trellio/jsonprotocol.py
trellio/manage.py
trellio/packet.py
trellio/pinger.py
trellio/protocol_factory.py
trellio/pubsub.py
trellio/registry.py
trellio/registry_client.py
trellio/sendqueue.py
trellio/services.py
trellio/signals.py
trellio/views.py
trellio/wrappers.py
trellio.egg-info/PKG-INFO
trellio.egg-info/SOURCES.txt
trellio.egg-info/dependency_links.txt
trellio.egg-info/requires.txt
trellio.egg-info/top_level.txt
trellio/conf_manager/__init__.py
trellio/conf_manager/conf_client.py
trellio/management/__init__.py
trellio/management/core.py
trellio/management/exceptions.py
trellio/management/commands/__init__.py
trellio/management/commands/base.py
trellio/management/commands/start.py
trellio/utils/__init__.py
trellio/utils/async_utils.py
trellio/utils/decorators.py
trellio/utils/helpers.py
trellio/utils/jsonencoder.py
trellio/utils/log.py
trellio/utils/log_handlers.py
trellio/utils/ordered_class_member.py
trellio/utils/stats.py