Metadata-Version: 1.0
Name: trellio
Version: 1.1.34
Summary: Python3 asyncio based micro-framework for micro-service architecture
Home-page: https://github.com/artificilabs/trellio.git
Author: Abhishek Verma, Nirmal Singh
Author-email: ashuverma1989@gmail.com, nirmal.singh.cer08@itbhu.ac.in
License: UNKNOWN
Keywords: asyncio,microservice,microframework,aiohttp
Platform: UNKNOWN
